pytorchrl/__init__.py
pytorchrl/learner.py
pytorchrl/trainer.py
pytorchrl/utils.py
pytorchrl/agent/__init__.py
pytorchrl/agent/actors/__init__.py
pytorchrl/agent/actors/base.py
pytorchrl/agent/actors/model_based_planner_actor.py
pytorchrl/agent/actors/off_policy_actor.py
pytorchrl/agent/actors/on_policy_actor.py
pytorchrl/agent/actors/utils.py
pytorchrl/agent/actors/distributions/__init__.py
pytorchrl/agent/actors/distributions/categorical.py
pytorchrl/agent/actors/distributions/deterministic.py
pytorchrl/agent/actors/distributions/gaussian.py
pytorchrl/agent/actors/distributions/squashed_gaussian.py
pytorchrl/agent/actors/feature_extractors/__init__.py
pytorchrl/agent/actors/feature_extractors/cnn.py
pytorchrl/agent/actors/feature_extractors/dictnet.py
pytorchrl/agent/actors/feature_extractors/embedding.py
pytorchrl/agent/actors/feature_extractors/ensemble_layer.py
pytorchrl/agent/actors/feature_extractors/fixup_cnn.py
pytorchrl/agent/actors/feature_extractors/gpt.py
pytorchrl/agent/actors/feature_extractors/mlp.py
pytorchrl/agent/actors/feature_extractors/utils.py
pytorchrl/agent/actors/memory_networks/__init__.py
pytorchrl/agent/actors/memory_networks/gru_net.py
pytorchrl/agent/actors/memory_networks/lstm_encoder_decoder_net.py
pytorchrl/agent/actors/memory_networks/lstm_net.py
pytorchrl/agent/actors/noise/__init__.py
pytorchrl/agent/actors/noise/gaussian.py
pytorchrl/agent/actors/noise/nonoise.py
pytorchrl/agent/actors/noise/ou.py
pytorchrl/agent/actors/reward_functions/__init__.py
pytorchrl/agent/actors/reward_functions/gym_reward_functions.py
pytorchrl/agent/actors/reward_functions/pybullet_reward_functions.py
pytorchrl/agent/actors/world_models/__init__.py
pytorchrl/agent/actors/world_models/utils.py
pytorchrl/agent/actors/world_models/world_model.py
pytorchrl/agent/algorithms/__init__.py
pytorchrl/agent/algorithms/base.py
pytorchrl/agent/algorithms/utils.py
pytorchrl/agent/algorithms/model_based/__init__.py
pytorchrl/agent/algorithms/model_based/mpc_cem.py
pytorchrl-3.2.15.dist-info/LICENCE
pytorchrl-3.2.15.dist-info/METADATA
pytorchrl-3.2.15.dist-info/WHEEL
pytorchrl-3.2.15.dist-info/top_level.txt
pytorchrl-3.2.15.dist-info/RECORD
