Metadata-Version: 2.1
Name: pytorchrl
Version: 3.2.15
Summary: Disributed RL implementations with ray and pytorch.
Home-page: https://github.com/PyTorchRL/pytorchrl/
Author: albertbou92
Author-email: 
Classifier: Programming Language :: Python :: 3
Classifier: License :: OSI Approved :: MIT License
Classifier: Operating System :: OS Independent
License-File: LICENCE
Requires-Dist: gym (==0.26.2)
Requires-Dist: ray[default]
Requires-Dist: numpy
Requires-Dist: pandas
Requires-Dist: scipy
Requires-Dist: lz4
Requires-Dist: tqdm
